Workbook

Sheet 23.8.17含税-德州-隋总
A1: 成 本 分 析 表 | J1: 一个月50万米，货到德州
H2: 编号: | I2: NONUL001 | L2: 德州隋总要单价
A3: 客户： | G3: 分析日期： | H3: 45155 | J3: 预留三方费用0.5%
A4: 结构： | B4: 45/0.12TS*2C | G4: 品名规格： | H4: NONUL 2X20AWG
A5: 序号 | B5: 制程 | C5: 规格 | G5: 单位用量 | H5: 单价 | I5: 材料金额
G6: KG/100M | H6: RMB/KG | I6: RMB/100M
A7: 1 | B7: 铜绞 | C7: 45/0.12TS*2C | G7: =0.12^2*0.7854*8.89/10*45*1.015*1.015*2 -> 0.93224432 | H7: =(J7+1300)/1.13/1000+5.41 -> 68.507345 | I7: =G7*H7 -> 63.865583 | J7: 70000
C8: 250D尼龙 | G8: 0.04 | H8: 14.7 | I8: =G8*H8 -> 0.588
A9: 2 | B9: 芯押 | C9: 敬信阻燃PP,PA1120001 ID:1.4mm*2C | G9: =(1.4^2-0.93^2*0.85)*0.7854*1.04/10*1.015*2 -> 0.20309436 | H9: =34.5/1.13 -> 30.530973 | I9: =G9*H9 -> 6.2006685 | J9: 含税34.5元
A10: 4 | B10: 外被 | C10: C86010108 OD:3.8mm | G10: =(3.85^2-1.4^2*2)*0.7854*1.47/10 -> 1.2587351 | H10: 9.21 | I10: =G10*H10 -> 11.59295
A11: 材料成本 | B11: =I11/100 -> 0.82247201 | C11: RMB/M | G11: =SUM(G7:G10)/100 -> 0.024340737 | H11: Kg | I11: =SUM(I7:I10) -> 82.247201 | J11: =B11*1.13/I22 -> 0.72831233
A12: 制程 | B12: 標准工時(一台机1KM开机时间) | C12: 损耗时间(1km) | D12: 固定费用率 | E12: 固定費用 | F12: 开机损耗废线（100M/每根芯线） | G12: 每个制程总废胶(KG) | H12: 金额 | I12: 費用成本小計
A13: 铜绞 | B13: =0.3*2 -> 0.6 | C13: 0 | D13: 10 | E13: =B13*D13*G20/1000+C13*D13*G18 -> 300 | F13: 0.5 | G13: 0 | H13: =F13*I7 -> 31.932792 | I13: =E13+H13*G18 -> 331.93279
A14: 芯押 | B14: =1000/60/200*2 -> 0.16666667 | C14: 0 | D14: 110 | E14: =B14*D14*G20/1000+C14*D14*G18 -> 916.66667 | F14: 0.5 | G14: 2 | H14: =F14*(I9+I7)+G14*H9 -> 96.095073 | I14: =E14+H14*G18 -> 1012.7617
A15: 集合 | B15: =1000/60/30 -> 0.55555556 | C15: 0 | D15: 40 | E15: =B15*D15*G20/1000+C15*D15*G18 -> 1111.1111 | F15: 0.2 | G15: 0 | H15: =F15*(I11-I10) -> 14.13085 | I15: =E15+H15*G18 -> 1125.242
A16: 外被 | B16: =1000/60/60 -> 0.27777778 | C16: 0 | D16: 140 | E16: =B16*D16*G20/1000+C16*D16*G18 -> 1944.4444 | F16: 0.5 | G16: 10 | H16: =F16*I11+G16*H10 -> 133.2236 | I16: =E16+H16*G18 -> 2077.668
A17: 其他费用 | C17: UL标签费(RMB/M) | D17: 运输费(RMB/KG) | E17: 包装费(RMB/M) | F17: 废品损耗(%) | G17: 订单开机次数 | H17: 费用总计 | I17: =SUM(I13:I16) -> 4547.6045
C18: 0 | D18: 0.3 | E18: 0.0037 | F18: 0.025 | G18: 1 | H18: 成本(RMB/M) | I18: 取利售价（RMB/M）
C19: 其他费用 | D19: 净利率 | E19: 报关费(RMB/次) | F19: 增值税率 | G19: 订单米数
C20: 0 | D20: 0.08 | E20: 0 | F20: 0.13 | G20: 50000 | H20: =I17/G20+B11+B11*F18 -> 0.93398591 | I20: =(H20/(1-D20)+C18+E18+E20/G20+C20/G20+C22*D22+D18*G11)*(1+F20)*(1+E22+F22) -> 1.261541
C21: 照射芯数 | D21: 照射费用(RMB/M) | E21: 营业费用率 | F21: 月结利息 | G21: 企税税率 | H21: 不取利售价（RMB/M） | I21: 最终售价（RMB/M）
C22: 1 | D22: 0.03 | E22: =0.7%+0.5% -> 0.012 | F22: =0.5%*3+0.5%*6 -> 0.045 | G22: 0.15 | H22: =(H20+C18+E18+E20/G20+C20/G20+C22*D22+D18*G11)*(1+F20)*(1+E22+F22) -> 1.1645356 | I22: =I20+(I20-H22)*G22 -> 1.2760918

Sheet 23.8.17未税-德州2
A1: 成 本 分 析 表 | J1: 一个月50万米，货到德州，月结90天电汇 | L1: 23.8.17日李其峰确认最低成本
H2: 编号: | I2: NONUL002 | L2: 德州隋总要单价
A3: 客户： | G3: 分析日期： | H3: 45155 | J3: 剃须刀的充电线
A4: 结构： | B4: 45/0.12BC*2C | G4: 品名规格： | H4: NONUL 2X20AWG
A5: 序号 | B5: 制程 | C5: 规格 | G5: 单位用量 | H5: 单价 | I5: 材料金额
G6: KG/100M | H6: RMB/KG | I6: RMB/100M
A7: 1 | B7: 铜绞 | C7: 45/0.12BC*2C | G7: =0.118^2*0.7854*8.89/10*45*1.015*1.015*2 -> 0.90142846 | H7: =(J7+1300)/1.13/1000+2.5 -> 65.597345 | I7: =G7*H7 -> 59.131314 | J7: 70000
C8: 250D尼龙 | G8: 0.04 | H8: 14.7 | I8: =G8*H8 -> 0.588
A9: 2 | B9: 芯押 | C9: PP ID:1.28mm*2C | G9: =(1.28^2-0.93^2*0.85)*0.7854*0.9/10*1.015*2 -> 0.12960752 | H9: 9.7345 | I9: =G9*H9 -> 1.2616644 | J9: PA3015001
A10: 4 | B10: 外被 | C10: C86010103 OD:3.3mm | G10: =(3.35^2-1.28^2*2)*0.7854*1.43/10 -> 0.89239905 | H10: =7.4+0.3 -> 7.7 | I10: =G10*H10 -> 6.8714727
A11: 材料成本 | B11: =I11/100 -> 0.67852451 | C11: RMB/M | G11: =SUM(G7:G10)/100 -> 0.01963435 | H11: Kg | I11: =SUM(I7:I10) -> 67.852451 | J11: =B11/I22 -> 0.81982575 | K11: =G11*G20 -> 1963.435
A12: 制程 | B12: 標准工時(一台机1KM开机时间) | C12: 损耗时间(1km) | D12: 固定费用率 | E12: 固定費用 | F12: 开机损耗废线（100M/每根芯线） | G12: 每个制程总废胶(KG) | H12: 金额 | I12: 費用成本小計
A13: 铜绞 | B13: =0.24*2 -> 0.48 | C13: 0 | D13: 10 | E13: =B13*D13*G20/1000+C13*D13*G18 -> 480 | F13: 0.5 | G13: 0 | H13: =F13*I7 -> 29.565657 | I13: =E13+H13*G18 -> 509.56566
A14: 芯押 | B14: =1000/60/200*2 -> 0.16666667 | C14: 0 | D14: 110 | E14: =B14*D14*G20/1000+C14*D14*G18 -> 1833.3333 | F14: 0.5 | G14: 2 | H14: =F14*(I9+I7)+G14*H9 -> 49.665489 | I14: =E14+H14*G18 -> 1882.9988
A15: 集合 | B15: 0 | C15: 0 | D15: 40 | E15: =B15*D15*G20/1000+C15*D15*G18 -> 0 | F15: 0.2 | G15: 0 | H15: =F15*(I11-I10) -> 12.196196 | I15: =E15+H15*G18 -> 12.196196
A16: 外被 | B16: =1000/60/60 -> 0.27777778 | C16: 0 | D16: 140 | E16: =B16*D16*G20/1000+C16*D16*G18 -> 3888.8889 | F16: 0.5 | G16: 10 | H16: =F16*I11+G16*H10 -> 110.92623 | I16: =E16+H16*G18 -> 3999.8151
A17: 其他费用 | C17: UL标签费(RMB/M) | D17: 运输费(RMB/KG) | E17: 包装费(RMB/M) | F17: 废品损耗(%) | G17: 订单开机次数 | H17: 费用总计 | I17: =SUM(I13:I16) -> 6404.5758
C18: 0 | D18: 0.215 | E18: 0.0037 | F18: 0.02 | G18: 1 | H18: 成本(RMB/M) | I18: 取利售价（RMB/M） | J18: =D18*G11/I22 -> 0.0051004796 | K18: =D18*G11 -> 0.0042213853
C19: 其他费用 | D19: 净利率 | E19: 报关费(RMB/次) | F19: 增值税率 | G19: 订单米数
C20: 0 | D20: 0.05 | E20: 0 | F20: 0 | G20: 100000 | H20: =I17/G20+B11+B11*F18 -> 0.75614076 | I20: =(H20/(1-D20)+C18+E18+E20/G20+C20/G20+C22*D22+D18*G11)*(1+F20)*(1+E22+F22) -> 0.82154392
C21: 照射芯数 | D21: 照射费用(RMB/M) | E21: 营业费用率 | F21: 月结利息 | G21: 企税税率 | H21: 不取利售价（RMB/M） | I21: 最终售价（RMB/M） | J21: 惠州单价0.76
C22: 0 | D22: 0 | E22: =0.7% -> 0.007 | F22: =0.5%*3 -> 0.015 | G22: 0.15 | H22: =(H20+C18+E18+E20/G20+C20/G20+C22*D22+D18*G11)*(1+F20)*(1+E22+F22) -> 0.78087151 | I22: =I20+(I20-H22)*G22 -> 0.82764479 | J22: 0.76 | K22: =I22/J22-1 -> 0.089006297

Sheet 23.8.29未税单价-惠州
A1: 惠州德泓单价
A2: 序号 | B2: 品名 | C2: 规格 | D2: 成本分析号 | E2: 未税单价 | F2: 利润 | G2: 材料占比 | H2: 备注 | I2: 三位小数售价
A3: 1 | B3: HVSF 0.5mm2*1C | C3: 20/0.180TC*1C 低毒PVC外被 ID:2.5mm | D3: HVSF002 | E3: ='23.8.29未税成本-惠州'!I18 -> 0.41683202 | F3: ='23.8.29未税成本-惠州'!D16 -> 0.05 | G3: ='23.8.29未税成本-惠州'!J9 -> 0.84567559 | I3: =ROUND(E3,3) -> 0.417
A4: 2 | B4: HVSF 0.75mm2*1C | C4: 30/0.180TC*1C 低毒PVC外被 ID:2.7mm | D4: HVSF001 | E4: ='23.8.29未税成本-惠州'!I36 -> 0.59492963 | F4: ='23.8.29未税成本-惠州'!D34 -> 0.05 | G4: ='23.8.29未税成本-惠州'!J27 -> 0.85669421 | I4: =ROUND(E4,3) -> 0.595
A5: 3 | B5: UL1007 16AWG | C5: 26/0.254TC*1C 低毒PVC外被 OD:2.4mm | D5: W100716003 | E5: ='23.8.29未税成本-惠州'!I54 -> 0.93970775 | F5: ='23.8.29未税成本-惠州'!D52 -> 0.05 | G5: ='23.8.29未税成本-惠州'!J45 -> 0.87327648 | I5: =ROUND(E5,3) -> 0.94
A6: 4 | B6: UL1007 22AWG | C6: 17/0.16TC*1C 低毒PVC外被 OD:1.6mm | D6: W100722001 | E6: ='23.8.29未税成本-惠州'!I72 -> 0.26369429 | F6: ='23.8.29未税成本-惠州'!D70 -> 0.05 | G6: ='23.8.29未税成本-惠州'!J63 -> 0.81892919 | I6: =ROUND(E6,3) -> 0.264
A7: 5 | B7: UL1007 26AWG | C7: 7/0.16TC*1C 低毒PVC外被 OD:1.3mm | D7: W100726001 | E7: ='23.8.29未税成本-惠州'!I90 -> 0.12638532 | F7: ='23.8.29未税成本-惠州'!D88 -> 0.05 | G7: ='23.8.29未税成本-惠州'!J81 -> 0.75070079 | I7: =ROUND(E7,3) -> 0.126
A8: 6 | B8: UL1015 16AWG | C8: 26/0.248TC*1C 低毒PVC外被 OD:3.1mm | D8: W101516002 | E8: ='23.8.29未税成本-惠州'!I108 -> 0.95903669 | F8: ='23.8.29未税成本-惠州'!D106 -> 0.05 | G8: ='23.8.29未税成本-惠州'!J99 -> 0.86904224 | I8: =ROUND(E8,3) -> 0.959
A9: 7 | B9: UL1015 18AWG | C9: 41/0.16TC*1C 低毒PVC外被 OD:2.8mm | D9: W101518002 | E9: ='23.8.29未税成本-惠州'!I126 -> 0.64459957 | F9: ='23.8.29未税成本-惠州'!D124 -> 0.05 | G9: ='23.8.29未税成本-惠州'!J117 -> 0.86117918 | I9: =ROUND(E9,3) -> 0.645
A10: 8 | B10: UL1015 20AWG | C10: 26/0.16TC*1C 低毒PVC外被 OD:2.55mm | D10: W101520002 | E10: ='23.8.29未税成本-惠州'!I144 -> 0.42888414 | F10: ='23.8.29未税成本-惠州'!D142 -> 0.05 | G10: ='23.8.29未税成本-惠州'!J135 -> 0.84630215 | I10: =ROUND(E10,3) -> 0.429
A11: 9 | B11: UL1015 22AWG | C11: 17/0.16TC*1C 低毒PVC外被 OD:2.40mm | D11: W101522002 | E11: ='23.8.29未税成本-惠州'!I162 -> 0.29974789 | F11: ='23.8.29未税成本-惠州'!D160 -> 0.05 | G11: ='23.8.29未税成本-惠州'!J153 -> 0.82510181 | I11: =ROUND(E11,3) -> 0.3
A12: 10 | B12: UL1061 26AWG | C12: 7/0.16TC*1C 低毒PVC外被 OD:1.0mm | D12: W106126001 | E12: ='23.8.29未税成本-惠州'!I180 -> 0.1258742 | F12: ='23.8.29未税成本-惠州'!D178 -> 0.05 | G12: ='23.8.29未税成本-惠州'!J171 -> 0.74357761 | I12: =ROUND(E12,3) -> 0.126
A13: 11 | B13: UL1061 28AWG | C13: 7/0.127TC*1C 低毒PVC外被 OD:0.90mm | D13: W106128002 | E13: ='23.8.29未税成本-惠州'!I198 -> 0.093493467 | F13: ='23.8.29未税成本-惠州'!D196 -> 0.05 | G13: ='23.8.29未税成本-惠州'!J189 -> 0.70111367 | I13: =ROUND(E13,3) -> 0.093
A14: 12 | B14: UL1569 16AWG | C14: 26/0.254TC*1C 低毒PVC外被 OD:2.3mm | D14: W156916001 | E14: ='23.8.29未税成本-惠州'!I216 -> 0.93636646 | F14: ='23.8.29未税成本-惠州'!D214 -> 0.05 | G14: ='23.8.29未税成本-惠州'!J207 -> 0.8712609 | I14: =ROUND(E14,3) -> 0.936
A15: 13 | B15: UL1569 20AWG | C15: 26/0.16TC*1C 低毒PVC外被 OD:1.8mm | D15: W156920001 | E15: ='23.8.29未税成本-惠州'!I234 -> 0.39667119 | F15: ='23.8.29未税成本-惠州'!D232 -> 0.05 | G15: ='23.8.29未税成本-惠州'!J225 -> 0.84450935 | I15: =ROUND(E15,3) -> 0.397
A16: 14 | B16: UL1569 22AWG | C16: 17/0.16TC*1C 低毒PVC外被 OD:1.6mm | D16: W156922001 | E16: ='23.8.29未税成本-惠州'!I252 -> 0.26505406 | F16: ='23.8.29未税成本-惠州'!D250 -> 0.05 | G16: ='23.8.29未税成本-惠州'!J243 -> 0.81578988 | I16: =ROUND(E16,3) -> 0.265
A17: 15 | B17: UL1569 26AWG | C17: 7/0.16TC*1C 低毒PVC外被 OD:1.30mm | D17: W156926001 | E17: ='23.8.29未税成本-惠州'!I270 -> 0.13067052 | F17: ='23.8.29未税成本-惠州'!D268 -> 0.05 | G17: ='23.8.29未税成本-惠州'!J261 -> 0.75357992 | I17: =ROUND(E17,3) -> 0.131
A18: 16 | B18: UL3271 16AWG 阻燃VW-1 | C18: 26/0.254TC*1C 125℃ XLPE 外被 OD:3.1mm | D18: W327116004 | E18: ='23.8.29未税成本-惠州'!I289 -> 1.6003513 | F18: ='23.8.29未税成本-惠州'!D287 -> 0.06 | G18: ='23.8.29未税成本-惠州'!J279 -> 0.83767409 | I18: =ROUND(E18,3) -> 1.6
A19: 17 | B19: UL3289 16AWG | C19: 26/0.254TC*1C UL150℃低毒XLPE OD:3.1mm | D19: W328916001 | E19: ='23.8.29未税成本-惠州'!I308 -> 1.4352152 | F19: ='23.8.29未税成本-惠州'!D306 -> 0.06 | G19: ='23.8.29未税成本-惠州'!J298 -> 0.816616 | H19: 无认证 | I19: =ROUND(E19,3) -> 1.435
A20: 18 | B20: UL3289 22AWG | C20: 17/0.16TC*1C UL150℃低毒XLPE OD:2.4mm | D20: W328922001 | E20: ='23.8.29未税成本-惠州'!I327 -> 0.5950592 | F20: ='23.8.29未税成本-惠州'!D325 -> 0.06 | G20: ='23.8.29未税成本-惠州'!J317 -> 0.77745039 | H20: 无认证 | I20: =ROUND(E20,3) -> 0.595
A21: 19 | B21: UL3289 26AWG | C21: 7/0.16TC*1C UL150℃低毒XLPE OD:2.1mm | D21: W328926001 | E21: ='23.8.29未税成本-惠州'!I346 -> 0.4021269 | F21: ='23.8.29未税成本-惠州'!D344 -> 0.06 | G21: ='23.8.29未税成本-惠州'!J336 -> 0.72740379 | H21: 无认证 | I21: =ROUND(E21,3) -> 0.402
A22: 20 | B22: UL3398 16AWG | C22: 26/0.254TC*1C UL150℃低毒XLPE OD:2.4mm | D22: W339816001 | E22: ='23.8.29未税成本-惠州'!I365 -> 1.1948545 | F22: ='23.8.29未税成本-惠州'!D363 -> 0.06 | G22: ='23.8.29未税成本-惠州'!J355 -> 0.82056896 | I22: =ROUND(E22,3) -> 1.195
A23: 21 | B23: UL3398 22AWG | C23: 17/0.16TC*1C UL150℃低毒XLPE OD:1.6mm | D23: W339822001 | E23: ='23.8.29未税成本-惠州'!I384 -> 0.4124518 | F23: ='23.8.29未税成本-惠州'!D382 -> 0.06 | G23: ='23.8.29未税成本-惠州'!J374 -> 0.74618262 | I23: =ROUND(E23,3) -> 0.412
A24: 22 | B24: UL3398 26AWG | C24: 7/0.16TC*1C UL150℃低毒XLPE OD:1.3mm | D24: W339826001 | E24: ='23.8.29未税成本-惠州'!I403 -> 0.24760062 | F24: ='23.8.29未税成本-惠州'!D401 -> 0.06 | G24: ='23.8.29未税成本-惠州'!J393 -> 0.64834407 | I24: =ROUND(E24,3) -> 0.248
A25: 23 | B25: UL10368 28AWG | C25: 7/0.127TC*1C 低毒XLPE外被 OD:0.9mm | D25: W1036828001 | E25: 不能辐照 | I25: ***

Sheet 23.8.29未税成本-惠州
A1: 成 本 分 析 表 | J1: 货到惠州，月结90天电汇 | L1: 23.8.17日李其峰确认最低成本
H2: 编号: | I2: HVSF002 | L2: 德州隋总要单价
A3: 客户： | G3: 分析日期： | H3: 45073 | J3: 900元/吨+300元送货费
A4: 结构： | B4: 20/0.180TC*1C | G4: 品名规格： | H4: HVSF 0.5mm2*1C
A5: 序号 | B5: 制程 | C5: 规格 | G5: 单位用量 | H5: 单价 | I5: 材料金额
G6: KG/100M | H6: RMB/KG | I6: RMB/100M
A7: 1 | B7: 铜绞 | C7: 20/0.178TC*1C | G7: =0.177^2*0.7854*8.89/10*20*1.015 -> 0.44405343 | H7: =(J7+1300)/1.13/1000+4.33 -> 67.427345 | I7: =G7*H7 -> 29.941344 | J7: 70000
A8: 2 | B8: 芯押 | C8: 低毒PVC ID:2.50 C550*X101 | G8: =(2.53^2-0.9^2*0.85)*0.7854*1.47/10 -> 0.65951829 | H8: 8.05 | I8: =G8*H8 -> 5.3091222
A9: 材料成本 | B9: =I9/100 -> 0.35250466 | C9: RMB/M | G9: =SUM(G7:G8)/100 -> 0.011035717 | H9: Kg | I9: =SUM(I7:I8) -> 35.250466 | J9: =B9/I18 -> 0.84567559 | K9: =G9*G16 -> 551.78586
A10: 制程 | B10: 標准工時(一台机1KM开机时间) | C10: 损耗时间(1km) | D10: 固定费用率 | E10: 固定費用 | F10: 开机损耗废线（100M/每根芯线） | G10: 每个制程总废胶(KG) | H10: 金额 | I10: 費用成本小計
A11: 铜绞 | B11: 0.218 | C11: 0 | D11: 10 | E11: =B11*D11*G16/1000+C11*D11*G14 -> 109 | F11: 0.5 | G11: 0 | H11: =F11*I7 -> 14.970672 | I11: =E11+H11*G14 -> 123.97067
A12: 芯押 | B12: =1000/60/220 -> 0.075757576 | C12: 0 | D12: 140 | E12: =B12*D12*G16/1000+C12*D12*G14 -> 530.30303 | F12: 2 | G12: 5 | H12: =F12*(I8+I7)+G12*H8 -> 110.75093 | I12: =E12+H12*G14 -> 641.05396
A13: 其他费用 | C13: UL标签费(RMB/M) | D13: 运输费(RMB/KG) | E13: 包装费(RMB/M) | F13: 废品损耗(%) | G13: 订单开机次数 | H13: 费用总计 | I13: =SUM(I11:I12) -> 765.02463
C14: 0 | D14: 0.9 | E14: 0.0015 | F14: 0.013 | G14: 1 | H14: 成本(RMB/M) | I14: 取利售价（RMB/M）
C15: 送货费 | D15: 净利率 | E15: 报关费(RMB/次) | F15: 增值税率 | G15: 订单米数
C16: =300/200000*G16 -> 75 | D16: 0.05 | E16: 0 | F16: 0 | G16: 50000 | H16: =I13/G16+B9+B9*F14 -> 0.37238771 | I16: =(H16/(1-D16)+C14+E14+E16/G16+C16/G16+C18*D18+D14*G9)*(1+F16)*(1+E18+F18) -> 0.41382744
C17: 照射芯数 | D17: 照射费用(RMB/M) | E17: 营业费用率 | F17: 月结利息 | G17: 企税税率 | H17: 不取利售价（RMB/M） | I17: 最终售价（RMB/M）
C18: 0 | D18: 0 | E18: =0.7% -> 0.007 | F18: =0.5%*3 -> 0.015 | G18: 0.15 | H18: =(H16+C14+E14+E16/G16+C16/G16+C18*D18+D14*G9)*(1+F16)*(1+E18+F18) -> 0.3937969 | I18: =I16+(I16-H18)*G18 -> 0.41683202
A19: 成 本 分 析 表
H20: 编号: | I20: HVSF001
A21: 客户： | G21: 分析日期： | H21: 45096
A22: 结构： | B22: 30/0.180TC*1C | G22: 品名规格： | H22: HVSF 0.75mm2*1C
A23: 序号 | B23: 制程 | C23: 规格 | G23: 单位用量 | H23: 单价 | I23: 材料金额
G24: KG/100M | H24: RMB/KG | I24: RMB/100M
A25: 1 | B25: 铜绞 | C25: 30/0.178TC*1C | G25: =0.177^2*0.7854*8.89/10*30*1.015 -> 0.66608014 | H25: =(J25+1300)/1.13/1000+4.33 -> 67.427345 | I25: =G25*H25 -> 44.912016 | J25: 70000
A26: 2 | B26: 芯押 | C26: 低毒PVC ID:2.70 C550*X101 | G26: =(2.75^2-1.11^2*0.85)*0.7854*1.47/10 -> 0.75220633 | H26: 8.05 | I26: =G26*H26 -> 6.055261
A27: 材料成本 | B27: =I27/100 -> 0.50967277 | C27: RMB/M | G27: =SUM(G25:G26)/100 -> 0.014182865 | H27: Kg | I27: =SUM(I25:I26) -> 50.967277 | J27: =B27/I36 -> 0.85669421 | K27: =G27*G34 -> 709.14324
A28: 制程 | B28: 標准工時(一台机1KM开机时间) | C28: 损耗时间(1km) | D28: 固定费用率 | E28: 固定費用 | F28: 开机损耗废线（100M/每根芯线） | G28: 每个制程总废胶(KG) | H28: 金额 | I28: 費用成本小計
A29: 铜绞 | B29: 0.24 | C29: 0 | D29: 10 | E29: =B29*D29*G34/1000+C29*D29*G32 -> 120 | F29: 0.5 | G29: 0 | H29: =F29*I25 -> 22.456008 | I29: =E29+H29*G32 -> 142.45601
A30: 芯押 | B30: =1000/60/200 -> 0.083333333 | C30: 0 | D30: 140 | E30: =B30*D30*G34/1000+C30*D30*G32 -> 583.33333 | F30: 2 | G30: 5 | H30: =F30*(I26+I25)+G30*H26 -> 142.18455 | I30: =E30+H30*G32 -> 725.51789
A31: 其他费用 | C31: UL标签费(RMB/M) | D31: 运输费(RMB/KG) | E31: 包装费(RMB/M) | F31: 废品损耗(%) | G31: 订单开机次数 | H31: 费用总计 | I31: =SUM(I29:I30) -> 867.97389
C32: 0 | D32: 0.9 | E32: 0.0019 | F32: 0.013 | G32: 1 | H32: 成本(RMB/M) | I32: 取利售价（RMB/M）
C33: 送货费 | D33: 净利率 | E33: 报关费(RMB/次) | F33: 增值税率 | G33: 订单米数
C34: =300/200000*G34 -> 75 | D34: 0.05 | E34: 0 | F34: 0 | G34: 50000 | H34: =I31/G34+B27+B27*F32 -> 0.53365799 | I34: =(H34/(1-D34)+C32+E32+E34/G34+C34/G34+C36*D36+D32*G27)*(1+F34)*(1+E36+F36) -> 0.59062385
C35: 照射芯数 | D35: 照射费用(RMB/M) | E35: 营业费用率 | F35: 月结利息 | G35: 企税税率 | H35: 不取利售价（RMB/M） | I35: 最终售价（RMB/M）
C36: 0 | D36: 0 | E36: =0.7% -> 0.007 | F36: =0.5%*3 -> 0.015 | G36: 0.15 | H36: =(H34+C32+E32+E34/G34+C34/G34+C36*D36+D32*G27)*(1+F34)*(1+E36+F36) -> 0.56191867 | I36: =I34+(I34-H36)*G36 -> 0.59492963
A37: 成 本 分 析 表
H38: 编号: | I38: W100716003
A39: 客户： | G39: 分析日期： | H39: 45029
A40: 结构： | B40: 26/0.254TC*1C | G40: 品名规格： | H40: UL1007 16AWG
A41: 序号 | B41: 制程 | C41: 规格 | G41: 单位用量 | H41: 单价 | I41: 材料金额
G42: KG/100M | H42: RMB/KG | I42: RMB/100M
A43: 1 | B43: 铜绞 | C43: 26/0.254TC*1C | G43: =0.252^2*0.7854*8.89/10*1.015*26 -> 1.1701273 | H43: =(J43+1300)/1.13/1000+3.79 -> 66.887345 | I43: =G43*H43 -> 78.266712 | J43: 70000
A44: 2 | B44: 外被 | C44: C24510101 C245***01外被 OD:2.4mm | G44: =(2.45^2-1.48^2*0.85)*0.7854*1.47/10 -> 0.47805493 | H44: 7.94 | I44: =G44*H44 -> 3.7957562
A45: 材料成本 | B45: =I45/100 -> 0.82062468 | C45: RMB/M | G45: =SUM(G43:G44)/100 -> 0.016481823 | H45: Kg | I45: =SUM(I43:I44) -> 82.062468 | J45: =B45/I54 -> 0.87327648 | K45: =G45*G52 -> 824.09114
A46: 制程 | B46: 標准工時(一台机1KM开机时间) | C46: 损耗时间(1km) | D46: 固定费用率 | E46: 固定費用 | F46: 开机损耗废线（100M/每根芯线） | G46: 每个制程总废胶(KG) | H46: 金额 | I46: 費用成本小計
A47: 铜绞 | B47: 0.24 | C47: 0 | D47: 10 | E47: =B47*D47*G52/1000+C47*D47*G50 -> 120 | F47: 0.5 | G47: 0 | H47: =F47*I43 -> 39.133356 | I47: =E47+H47*G50 -> 159.13336
A48: 外被 | B48: =1000/60/220 -> 0.075757576 | C48: 0 | D48: 140 | E48: =B48*D48*G52/1000+C48*D48*G50 -> 530.30303 | F48: 1.5 | G48: 2 | H48: =F48*I45+G48*H44 -> 138.9737 | I48: =E48+H48*G50 -> 669.27673
A49: 其他费用 | C49: UL标签费(RMB/M) | D49: 运输费(RMB/KG) | E49: 包装费(RMB/M) | F49: 废品损耗(%) | G49: 订单开机次数 | H49: 费用总计 | I49: =SUM(I47:I48) -> 828.41009
C50: =0.0074/3 -> 0.0024666667 | D50: 0.9 | E50: 0.0015 | F50: 0.013 | G50: 1 | H50: 成本(RMB/M) | I50: 取利售价（RMB/M）
C51: 送货费 | D51: 净利率 | E51: 报关费(RMB/次) | F51: 增值税率 | G51: 订单米数
C52: =300/200000*G52 -> 75 | D52: 0.05 | E52: 0 | F52: 0 | G52: 50000 | H52: =I49/G52+B45+B45*F50 -> 0.847861 | I52: =(H52/(1-D52)+C50+E50+E52/G52+C52/G52+C54*D54+D50*G45)*(1+F52)*(1+E54+F54) -> 0.93286685
C53: 照射芯数 | D53: 照射费用(RMB/M) | E53: 营业费用率 | F53: 月结利息 | G53: 企税税率 | H53: 不取利售价（RMB/M） | I53: 最终售价（RMB/M）
C54: 0 | D54: 0 | E54: =0.7% -> 0.007 | F54: =0.5%*3 -> 0.015 | G54: 0.15 | H54: =(H52+C50+E50+E52/G52+C52/G52+C54*D54+D50*G45)*(1+F52)*(1+E54+F54) -> 0.88726086 | I54: =I52+(I52-H54)*G54 -> 0.93970775
A55: 成 本 分 析 表
H56: 编号: | I56: W100722001
A57: 客户： | B57: 轴装 300轴 2135米/轴 | G57: 分析日期： | H57: 45120
A58: 结构： | B58: 17/0.16TC*1C | G58: 品名规格： | H58: UL1007 22AWG
A59: 序号 | B59: 制程 | C59: 规格 | G59: 单位用量 | H59: 单价 | I59: 材料金额
G60: KG/100M | H60: RMB/KG | I60: RMB/100M
A61: 1 | B61: 铜绞 | C61: 17/0.155TC*1C | G61: =0.155^2*0.7854*8.89/10*17*1.015 -> 0.28944831 | H61: =(J61+1300)/1.13/1000+4.49 -> 67.587345 | I61: =G61*H61 -> 19.563043 | J61: 70000
A62: 2 | B62: 外被 | C62: C245*X101外被 OD:1.6mm | G62: =(1.63^2-0.72^2*0.85)*0.7854*1.47/10 -> 0.25587564 | H62: 7.94 | I62: =G62*H62 -> 2.0316526
A63: 材料成本 | B63: =I63/100 -> 0.21594695 | G63: =SUM(G61:G62)/100 -> 0.0054532395 | H63: Kg | I63: =SUM(I61:I62) -> 21.594695 | J63: =B63/I72 -> 0.81892919 | K63: =G63*G70 -> 272.66197
A64: 制程 | B64: 標准工時(一台机1KM开机时间) | C64: 损耗时间(1km) | D64: 固定费用率 | E64: 固定費用 | F64: 开机损耗废线（100M/每根芯线） | G64: 每个制程总废胶(KG) | H64: 金额 | I64: 費用成本小計
A65: 铜绞 | B65: 0.286 | C65: 0 | D65: 10 | E65: =B65*D65*G70/1000+C65*D65*G68 -> 143 | F65: 0.5 | G65: 0 | H65: =F65*I61 -> 9.7815214 | I65: =E65+H65*G68 -> 152.78152
A66: 外被 | B66: =1000/60/250 -> 0.066666667 | C66: 0 | D66: 120 | E66: =B66*D66*G70/1000+C66*D66*G68 -> 400 | F66: 1.5 | G66: 2 | H66: =F66*I63+G66*H62 -> 48.272043 | I66: =E66+H66*G68 -> 448.27204
A67: 其他费用 | C67: UL标签费(RMB/M) | D67: 运输费(RMB/KG) | E67: 包装费(RMB/M) | F67: 废品损耗(%) | G67: 订单开机次数 | H67: 费用总计 | I67: =SUM(I65:I66) -> 601.05356
C68: =0.0074/3 -> 0.0024666667 | D68: 0.9 | E68: 0.0044 | F68: 0.013 | G68: 1 | H68: 成本(RMB/M) | I68: 取利售价（RMB/M）
C69: 送货费 | D69: 净利率 | E69: 报关费(RMB/次) | F69: 增值税率 | G69: 订单米数
C70: =300/200000*G70 -> 75 | D70: 0.05 | E70: 0 | F70: 0 | G70: 50000 | H70: =I67/G70+B63+B63*F68 -> 0.23077534 | I70: =(H70/(1-D70)+C68+E68+E70/G70+C70/G70+C72*D72+D68*G63)*(1+F70)*(1+E72+F72) -> 0.2618323
C71: 照射芯数 | D71: 照射费用(RMB/M) | E71: 营业费用率 | F71: 月结利息 | G71: 企税税率 | H71: 不取利售价（RMB/M） | I71: 最终售价（RMB/M）
C72: 0 | D72: 0 | E72: =0.7% -> 0.007 | F72: =0.5%*3 -> 0.015 | G72: 0.15 | H72: =(H70+C68+E68+E70/G70+C70/G70+C72*D72+D68*G63)*(1+F70)*(1+E72+F72) -> 0.24941902 | I72: =I70+(I70-H72)*G72 -> 0.26369429
A73: 成 本 分 析 表
H74: 编号: | I74: W100726001
A75: 客户： | B75: 轴装 300型 3050米 | G75: 分析日期： | H75: 45120
A76: 结构： | B76: 7/0.16TC*1C | G76: 品名规格： | H76: UL1007 26AWG
A77: 序号 | B77: 制程 | C77: 规格 | G77: 单位用量 | H77: 单价 | I77: 材料金额
G78: KG/100M | H78: RMB/KG | I78: RMB/100M
A79: 1 | B79: 铜绞 | C79: 7/0.155TC*1C | G79: =0.155^2*0.7854*8.89/10*7*1.015 -> 0.1191846 | H79: =(J79+1300)/1.13/1000+4.49 -> 67.587345 | I79: =G79*H79 -> 8.0553706 | J79: 70000
A80: 2 | B80: 外被 | C80: C245***01外被 OD:1.3mm | G80: =(1.32^2-0.46^2*0.85)*0.7854*1.47/10 -> 0.18040118 | H80: 7.94 | I80: =G80*H80 -> 1.4323854
A81: 材料成本 | B81: =I81/100 -> 0.094877559 | G81: =SUM(G79:G80)/100 -> 0.0029958578 | H81: Kg | I81: =SUM(I79:I80) -> 9.4877559 | J81: =B81/I90 -> 0.75070079 | K81: =G81*G88 -> 149.79289
A82: 制程 | B82: 標准工時(一台机1KM开机时间) | C82: 损耗时间(1km) | D82: 固定费用率 | E82: 固定費用 | F82: 开机损耗废线（100M/每根芯线） | G82: 每个制程总废胶(KG) | H82: 金额 | I82: 費用成本小計
A83: 铜绞 | B83: 0.4 | C83: 0 | D83: 8 | E83: =B83*D83*G88/1000+C83*D83*G86 -> 160 | F83: 0.5 | G83: 0 | H83: =F83*I79 -> 4.0276853 | I83: =E83+H83*G86 -> 164.02769
A84: 外被 | B84: =1000/60/270 -> 0.061728395 | C84: 0 | D84: 120 | E84: =B84*D84*G88/1000+C84*D84*G86 -> 370.37037 | F84: 1.5 | G84: 2 | H84: =F84*I81+G84*H80 -> 30.111634 | I84: =E84+H84*G86 -> 400.482
A85: 其他费用 | C85: UL标签费(RMB/M) | D85: 运输费(RMB/KG) | E85: 包装费(RMB/M) | F85: 废品损耗(%) | G85: 订单开机次数 | H85: 费用总计 | I85: =SUM(I83:I84) -> 564.50969
C86: =0.0074/3 -> 0.0024666667 | D86: 0.9 | E86: 0.0031 | F86: 0.013 | G86: 1 | H86: 成本(RMB/M) | I86: 取利售价（RMB/M）
C87: 送货费 | D87: 净利率 | E87: 报关费(RMB/次) | F87: 增值税率 | G87: 订单米数
C88: =300/200000*G88 -> 75 | D88: 0.05 | E88: 0 | F88: 0 | G88: 50000 | H88: =I85/G88+B81+B81*F86 -> 0.10740116 | I88: =(H88/(1-D88)+C86+E86+E88/G88+C88/G88+C90*D90+D86*G81)*(1+F88)*(1+E90+F90) -> 0.12551876
C89: 照射芯数 | D89: 照射费用(RMB/M) | E89: 营业费用率 | F89: 月结利息 | G89: 企税税率 | H89: 不取利售价（RMB/M） | I89: 最终售价（RMB/M）
C90: 0 | D90: 0 | E90: =0.7% -> 0.007 | F90: =0.5%*3 -> 0.015 | G90: 0.15 | H90: =(H88+C86+E86+E88/G88+C88/G88+C90*D90+D86*G81)*(1+F88)*(1+E90+F90) -> 0.11974171 | I90: =I88+(I88-H90)*G90 -> 0.12638532
A91: 成 本 分 析 表
H92: 编号: | I92: W101516002
A93: 客户： | G93: 分析日期： | H93: 45120
A94: 结构： | B94: 26/0.248TC*1C | G94: 品名规格： | H94: UL1015 16AWG
A95: 序号 | B95: 制程 | C95: 规格 | G95: 单位用量 | H95: 单价 | I95: 材料金额
G96: KG/100M | H96: RMB/KG | I96: RMB/100M
A97: 1 | B97: 铜绞 | C97: 26/0.248TC*1C | G97: =0.248^2*0.7854*8.89*1.015/10*26 -> 1.1332753 | H97: =(J97+1300)/1.13/1000+3.79 -> 66.887345 | I97: =G97*H97 -> 75.801774 | J97: 70000
A98: 2 | B98: 外被 | C98: C550*X101外被 OD:3.1mm | G98: =(3.15^2-1.48^2*0.85)*0.7854*1.48/10 -> 0.93696467 | H98: 8.05 | I98: =G98*H98 -> 7.5425656
A99: 材料成本 | B99: =I99/100 -> 0.83344339 | C99: RMB/M | G99: =SUM(G97:G98)/100 -> 0.020702399 | H99: Kg | I99: =SUM(I97:I98) -> 83.344339 | J99: =B99/I108 -> 0.86904224 | K99: =G99*G106 -> 1035.12
A100: 制程 | B100: 標准工時(一台机1KM开机时间) | C100: 损耗时间(1km) | D100: 固定费用率 | E100: 固定費用 | F100: 开机损耗废线（100M/每根芯线） | G100: 每个制程总废胶(KG) | H100: 金额 | I100: 費用成本小計
...

Sheet 隋总提供
A1: 零件料号 | B1: 产品规格 | C1: 成本分析号（青岛得润）
A2: Wire | B2: HVSF-0.5mm2(20/0.18TS) 105℃ PSE mark,Black，RoHS2.0 | C2: HVSF002
A3: Wire | B3: HVSF-0.5mm2(20/0.18TS) 105℃ PSE mark,Blue，RoHS2.0
A4: Wire | B4: HVSF-0.5mm2(20/0.18TS) 105℃ PSE mark,Brown，RoHS2.0
A5: Wire | B5: HVSF-0.5mm2(20/0.18TS) 105℃ PSE mark,GRAY，RoHS2.0
A6: Wire | B6: HVSF-0.75mm2(30/0.18TS) 105℃ PSE mark,Black，RoHS2.0 | C6: HVSF001
A7: Wire | B7: HVSF-0.75mm2(30/0.18TS) 105℃ PSE mark,Gray，RoHS2.0
A8: Wire | B8: HVSF-0.75mm2(30/0.18TS) 105℃ PSE mark,White，RoHS2.0
A9: Wire | B9: UL1007 16AWG Red | C9: W100716003
A10: Wire | B10: UL1007 16AWG White
A11: Wire | B11: UL1007 22AWG Blue | C11: W100722001
A12: Wire | B12: UL1007 22AWG Gray
A13: Wire | B13: UL1007 22AWG Orange
A14: Wire | B14: UL1007 22AWG Pink
A15: Wire | B15: UL1007 22AWG Red
A16: Wire | B16: UL1007 22AWG White
A17: Wire | B17: UL1007 22AWG Yellow
A18: WIRE | B18: UL1007 22AWG,BLUE,VW-1 UL,CSA认证，RoHS2.0
A19: WIRE | B19: UL1007 CSA TR-64 26AWG,RED,VW-1，RoHS2.0,无铅,不含DOP | C19: W100726001
A20: WIRE | B20: UL1007 CSA TR-64 26AWG,WHITE,VW-1，RoHS2.0,无铅,不含DOP
A21: WIRE | B21: UL1015 16AWG GREEN RoHS2.0 | C21: W101516002
A22: Wire | B22: UL1015 18AWG GREEN ROHS2.0 | C22: W101518002
A23: Wire | B23: UL1015 20AWG BLACK ROHS2.0 | C23: W101520002
A24: WIRE | B24: UL1015 20AWG BLUE,RoHS2.0
A25: Wire | B25: UL1015 20AWG WHITE ROHS2.0
A26: WIRE | B26: UL1015 22AWG GREEN RoHS2.0 | C26: W101522002
A27: WIRE | B27: UL1061 26AWG,BLACK,VW-1 UL认证，RoHS2.0,无铅,不含DOP | C27: W106126001
A28: WIRE | B28: UL1061 26AWG,RED,VW-1 UL认证，RoHS2.0,无铅,不含DOP
A29: WIRE | B29: UL1061 UL/CSA TR-64 26AWG,BLACK,VW-1 RoHS2.0,无铅,不含DOP | C29: W106126001
A30: WIRE | B30: UL1061 UL/CSA TR-64 26AWG,WHITE,VW-1 RoHS2.0,无铅,不含DOP
A31: WIRE | B31: UL1061 28AWG,BLUE OD:0.9mm VW-1 UL认证，RoHS2.0,无铅,不含DOP | C31: W106128002
A32: WIRE | B32: UL1061 28AWG,BROWN,OD:0.9mm VW-1 UL认证，RoHS2.0,无铅,不含DOP
A33: WIRE | B33: UL1061 28AWG,Gray OD:0.9mm VW-1 UL认证，RoHS2.0,无铅,不含DOP
A34: WIRE | B34: UL1061 28AWG,GREEN OD:0.9mm VW-1 UL认证，RoHS2.0,无铅,不含DOP
A35: WIRE | B35: UL1061 28AWG,ORANGE OD:0.9mm VW-1 UL认证，RoHS2.0,无铅,不含DOP
A36: WIRE | B36: UL1061 28AWG,RED,OD:0.9mm VW-1 UL认证，RoHS2.0,无铅,不含DOP
A37: WIRE | B37: UL1061 28AWG,VIOLET OD:0.9mm VW-1 UL认证，RoHS2.0,无铅,不含DOP
A38: WIRE | B38: UL1061 28AWG,WHITE,VW-1 UL认证，RoHS2.0,无铅,不含DOP
A39: WIRE | B39: UL1061 28AWG,YELLOW OD:0.9mm VW-1 UL认证，RoHS2.0,无铅,不含DOP
A40: WIRE | B40: UL1061 CSA TR-64 28AWG,BLUE,VW-1 RoHS2.0,无铅,不含DOP
A41: WIRE | B41: UL1061 CSA TR-64 28AWG,WHITE,VW-1 RoHS2.0,无铅,不含DOP
A42: Wire | B42: UL1569 16AWG Blue | C42: W156916001
A43: Wire | B43: UL1569 16AWG Brown
A44: WIRE | B44: UL1569 16AWG GREEN,RoHS2.0
A45: Wire | B45: UL1569 16AWG White
A46: WIRE | B46: UL1569 20AWG BROWN,RoHS2.0 | C46: W156920001
A47: WIRE | B47: UL1569 20AWG GREEN,RoHS2.0
A48: WIRE | B48: UL1569 20AWG ORANGE,RoHS2.0
A49: WIRE | B49: UL1569 20AWG WHITE,RoHS2.0
A50: WIRE | B50: UL1569 22AWG BLACK,RoHS2.0 | C50: W156922001
A51: Wire | B51: UL1569 22AWG Brown
A52: WIRE | B52: UL1569 22AWG GREEN,RoHS2.0
A53: Wire | B53: UL1569 22AWG Orange
A54: WIRE | B54: UL1569 22AWG RED,RoHS2.0
A55: Wire | B55: UL1569 22AWG Violet
A56: Wire | B56: UL1569 22AWG White
A57: Wire | B57: UL1569 26AWG BLACK ROHS2.0 | C57: W156926001
A58: WIRE | B58: UL1569 26AWG BLUE,RoHS2.0
A59: WIRE | B59: UL1569 26AWG BROWN,RoHS2.0
A60: Wire | B60: UL1569 26AWG GRAY ROHS2.0
A61: Wire | B61: UL1569 26AWG GREEN ROHS2.0
A62: Wire | B62: UL1569 26AWG ORANGE ROHS2.0
A63: Wire | B63: UL1569 26AWG PINK ROHS2.0
A64: Wire | B64: UL1569 26AWG RED ROHS2.0
A65: Wire | B65: UL1569 26AWG SKY BLUE ROHS2.0
A66: Wire | B66: UL1569 26AWG VOLET ROHS2.0
A67: WIRE | B67: UL1569 26AWG WHITE RoHS2.0
A68: Wire | B68: UL1569 26AWG YELLOW ROHS2.0
A69: WIRE | B69: UL10368 UL/CSA TR-64 28AWG,RED,VW-1 RoHS2.0,无铅,不含DOP | C69: W1036828001--不能辐照
A70: WIRE | B70: UL10368 UL/CSA TR-64 28AWG,WHITE,VW-1 RoHS2.0,无铅,不含DOP
A71: WIRE | B71: UL10368 UL/CSA TR-64 28AWG,YELLOW,VW-1 RoHS2.0,无铅,不含DOP
A72: WIRE | B72: UL3271 16AWG(26/0.254),ORANGE VW-1 UL认证，RoHS2.0,无铅,不含DOP | C72: W327116004
A73: WIRE | B73: UL3271 16AWG(26/0.254),RED VW-1 UL认证，RoHS2.0,无铅,不含DOP
A74: WIRE | B74: UL3271 16AWG(26/0.254),WHITE VW-1 UL认证，RoHS2.0,无铅,不含DOP
A75: WIRE | B75: UL3289 16AWG BLACK RoHS2.0 | C75: W328916001
A76: WIRE | B76: UL3289 16AWG GRAY RoHS2.0
A77: WIRE | B77: UL3289 16AWG ORANGE RoHS2.0
A78: WIRE | B78: UL3289 16AWG RED RoHS2.0
A79: WIRE | B79: UL3289 16AWG WHITE RoHS2.0
A80: WIRE | B80: UL3289 22AWG BLACK RoHS2.0 | C80: W328922001
A81: Wire | B81: UL3289 22AWG Blue
A82: WIRE | B82: UL3289 22AWG BROWN RoHS2.0
A83: WIRE | B83: UL3289 22AWG GRAY RoHS2.0
A84: Wire | B84: UL3289 22AWG Green
A85: WIRE | B85: UL3289 22AWG ORANGE RoHS2.0
A86: Wire | B86: UL3289 22AWG Red
A87: WIRE | B87: UL3289 22AWG WHITE RoHS2.0
A88: Wire | B88: UL3289 22AWG Yellow
A89: Wire | B89: UL3289 26AWG White | C89: W328926001
A90: WIRE | B90: UL3398 16AWG BLACK,RoHS2.0 | C90: W339816001
A91: WIRE | B91: UL3398 16AWG GRAR,RoHS2.0
A92: WIRE | B92: UL3398 16AWG ORANGE,RoHS2.0
A93: WIRE | B93: UL3398 16AWG RED,RoHS2.0
A94: WIRE | B94: UL3398 16AWG WHITE,RoHS2.0
A95: WIRE | B95: UL3398 22AWG BLACK,RoHS2.0 | C95: W339822001
A96: WIRE | B96: UL3398 22AWG BLUE,RoHS2.0
A97: WIRE | B97: UL3398 22AWG BROWN,RoHS2.0
A98: WIRE | B98: UL3398 22AWG GRAY,RoHS2.0
A99: WIRE | B99: UL3398 22AWG GREEN,RoHS2.0
A100: WIRE | B100: UL3398 22AWG ORANGE,RoHS2.0
...
